Metadata-Version: 2.1
Name: esu
Version: 3.0.2
Summary: Enjoy the flexibility of structs with esu!
Home-page: http://github.com/torokmark/esu
Author: Mark Torok
License: Apache License 2.0
Project-URL: Documentation, https://esu.readthedocs.io
Project-URL: Source, https://github.com/torokmark/esu
Platform: UNKNOWN
Classifier: Programming Language :: Python :: 3.5
Classifier: Programming Language :: Python :: 3.6
Classifier: Programming Language :: Python :: 3.7
Classifier: Programming Language :: Python :: 3.8
Classifier: Topic :: Software Development :: Libraries :: Python Modules
Requires-Python: >=3.5
